gisa/__init__.py
gisa/manisa.py
gisa-1.0.2.dist-info/LICENSE
gisa-1.0.2.dist-info/METADATA
gisa-1.0.2.dist-info/WHEEL
gisa-1.0.2.dist-info/top_level.txt
gisa-1.0.2.dist-info/RECORD
