Metadata-Version: 2.1
Name: gisa
Version: 1.0.2
Summary: Gisa is a Python package that converts numbers into Malagasy words.Returns its corresponding Malagasy word representation.
Home-page: https://github.com/mattnix4/gisa
Author: Matt Nix
Author-email: dorints.mg@gmail.com
License: UNKNOWN
Platform: UNKNOWN
Classifier: Programming Language :: Python :: 3
Classifier: Programming Language :: Python :: 3.7
Classifier: Programming Language :: Python :: 3.8
Classifier: Programming Language :: Python :: 3.9
Classifier: Programming Language :: Python :: 3.10
Classifier: Programming Language :: Python :: 3.11
Classifier: License :: OSI Approved :: MIT License
Classifier: Operating System :: OS Independent
Requires-Python: >=3.7
